pdfpop/__init__.py
pdfpop/__main__.py
pdfpop/cli.py
pdfpop/commands.py
pdfpop/form_config.py
pdfpop/pdf.py
pdfpop-0.5.0.dist-info/LICENSE-THIRD-PARTY.txt
pdfpop-0.5.0.dist-info/LICENSE.txt
pdfpop-0.5.0.dist-info/METADATA
pdfpop-0.5.0.dist-info/WHEEL
pdfpop-0.5.0.dist-info/entry_points.txt
pdfpop-0.5.0.dist-info/top_level.txt
pdfpop-0.5.0.dist-info/RECORD
