Metadata-Version: 2.1
Name: pdfpop
Version: 0.5.0
Summary: Populate a PDF with data from Microsoft Excel
Author-email: Ian Dinwoodie <dinwoodieian@gmail.com>
Project-URL: repository, https://github.com/iandinwoodie/pdfpop
Keywords: pdf,excel,populate
Classifier: Development Status :: 1 - Planning
Classifier: Programming Language :: Python :: 3
Classifier: License :: OSI Approved :: GNU General Public License v3 (GPLv3)
Classifier: Operating System :: OS Independent
Requires-Python: >=3.9
License-File: LICENSE-THIRD-PARTY.txt
License-File: LICENSE.txt
Requires-Dist: click (>=8.1.3)
Requires-Dist: openpyxl (>=3.0.9)
Requires-Dist: pandas (>=1.4.2)
Requires-Dist: pdfrw (>=0.4)
Requires-Dist: pytest (>=7.1.2)
Requires-Dist: pytest-mock (>=3.7.0)
Requires-Dist: pytest-cov (>=3.0.0)
